LICENSE.md
README.md
setup.cfg
setup.py
parse_pip_search/__init__.py
parse_pip_search/__main__.py
parse_pip_search/parse_pip_search.py
parse_pip_search/utils.py
parse_pip_search.egg-info/PKG-INFO
parse_pip_search.egg-info/SOURCES.txt
parse_pip_search.egg-info/dependency_links.txt
parse_pip_search.egg-info/entry_points.txt
parse_pip_search.egg-info/requires.txt
parse_pip_search.egg-info/top_level.txt