Metadata-Version: 2.1
Name: parse-pip-search
Version: 0.0.1
Summary: A parseable command-line package to search like pip used to, via PyPi
Home-page: https://github.com/marticliment/parseable_pip_search
Author: Martí Climent
Author-email: marticlilop@gmail.com
Classifier: Programming Language :: Python :: 3
Classifier: License :: OSI Approved :: MIT License
Classifier: Operating System :: OS Independent
Requires-Python: >=3.2
License-File: LICENSE.md
